Workbook

Sheet customers
A1: customer_id | B1: customer_name | C1: segment | D1: region | E1: city | F1: phone | G1: email | H1: join_date
A2: C001 | B2: Nguyễn Văn An | C2: Cá nhân | D2: Hà Nội | E2: Hà Nội | F2: 0901234567 | G2: an.nguyen@email.com | H2: 2023-01-15
A3: C002 | B3: Lê Thị Bích | C3: Cá nhân | D3: TP.HCM | E3: TP.HCM | F3: 0912345678 | G3: bich.le@email.com | H3: 2023-02-20
A4: C003 | B4: Công ty ABC | C4: Doanh nghiệp | D4: Đà Nẵng | E4: Đà Nẵng | F4: 0236123456 | G4: info@abc.com | H4: 2023-03-10
A5: C004 | B5: Hoàng Thị Dung | C5: Cá nhân | D5: Cần Thơ | E5: Cần Thơ | F5: 0923456789 | G5: dung.hoang@email.com | H5: 2023-04-05
A6: C005 | B6: Công ty XYZ | C6: Doanh nghiệp | D6: TP.HCM | E6: TP.HCM | F6: 0283456789 | G6: contact@xyz.com | H6: 2023-05-12
A7: C006 | B7: Vũ Văn Em | C7: Cá nhân | D7: Hà Nội | E7: Hà Nội | F7: 0934567890 | G7: em.vu@email.com | H7: 2023-06-18
A8: C007 | B8: Đặng Thị Fương | C8: Cá nhân | D8: Huế | E8: Huế | F8: 0234567890 | G8: fuong.dang@email.com | H8: 2023-07-22
A9: C008 | B9: Bùi Văn Giang | C9: Cá nhân | D9: Hà Nội | E9: Hà Nội | F9: 0945678901 | G9: giang.bui@email.com | H9: 2023-08-30
A10: C009 | B10: Lý Thị Hà | C10: Cá nhân | D10: TP.HCM | E10: TP.HCM | F10: 0956789012 | G10: ha.ly@email.com | H10: 2023-09-14
A11: C010 | B11: Công ty DEF | C11: Doanh nghiệp | D11: TP.HCM | E11: TP.HCM | F11: 0284567890 | G11: sales@def.com | H11: 2023-10-01
A12: C011 | B12: Phan Văn Inh | C12: Cá nhân | D12: Đà Nẵng | E12: Đà Nẵng | F12: 0967890123 | G12: inh.phan@email.com | H12: 2023-10-20
A13: C012 | B13: Hoàng Minh | C13: Cá nhân | D13: Đà Nẵng | E13: Đà Nẵng | F13: 0978901234 | G13: minh.hoang@email.com | H13: 2023-11-05

Sheet products
A1: product_id | B1: product_name | C1: category | D1: brand | E1: unit_price | F1: cost_price | G1: unit | H1: stock_qty | I1: status
A2: P001 | B2: Dell Inspiron 15 | C2: Laptop | D2: Dell | E2: 18500000 | F2: 12000000 | G2: Chiếc | H2: 50 | I2: Còn hàng
A3: P002 | B3: MacBook Air M2 | C3: Laptop | D3: Apple | E3: 32000000 | F3: 22000000 | G3: Chiếc | H3: 30 | I3: Còn hàng
A4: P003 | B4: HP Pavilion | C4: Laptop | D4: HP | E4: 14000000 | F4: 9500000 | G4: Chiếc | H4: 40 | I4: Còn hàng
A5: P004 | B5: iPhone 15 | C5: Điện thoại | D5: Apple | E5: 22000000 | F5: 16000000 | G5: Chiếc | H5: 80 | I5: Còn hàng
A6: P005 | B6: Samsung Galaxy S24 | C6: Điện thoại | D6: Samsung | E6: 18000000 | F6: 13000000 | G6: Chiếc | H6: 60 | I6: Còn hàng
A7: P006 | B7: Samsung 27inch | C7: Màn hình | D7: Samsung | E7: 6500000 | F7: 4200000 | G7: Chiếc | H7: 35 | I7: Còn hàng
A8: P007 | B8: LG 24inch | C8: Màn hình | D8: LG | E8: 4800000 | F8: 3100000 | G8: Chiếc | H8: 45 | I8: Còn hàng
A9: P008 | B9: Bàn phím cơ | C9: Phụ kiện | D9: Keychron | E9: 1200000 | F9: 700000 | G9: Chiếc | H9: 100 | I9: Còn hàng
A10: P009 | B10: Chuột Logitech | C10: Phụ kiện | D10: Logitech | E10: 850000 | F10: 500000 | G10: Chiếc | H10: 150 | I10: Còn hàng
A11: P010 | B11: Tai nghe Sony | C11: Phụ kiện | D11: Sony | E11: 2500000 | F11: 1600000 | G11: Chiếc | H11: 70 | I11: Còn hàng
A12: P011 | B12: USB-C Hub | C12: Phụ kiện | D12: Ugreen | E12: 650000 | F12: 380000 | G12: Chiếc | H12: 200 | I12: Còn hàng
A13: P012 | B13: Laptop Stand | C13: Phụ kiện | D13: Adjustable | E13: 450000 | F13: 250000 | G13: Chiếc | H13: 0 | I13: Hết hàng

Sheet sales_reps
A1: rep_id | B1: rep_name | C1: region | D1: email | E1: phone | F1: hire_date | G1: target_monthly | H1: commission_pct
A2: R001 | B2: Trần Minh | C2: Hà Nội | D2: tran.minh@company.com | E2: 0901111111 | F2: 2022-03-01 | G2: 300000000 | H2: 0.035
A3: R002 | B3: Phạm Hoa | C3: TP.HCM | D3: pham.hoa@company.com | E3: 0912222222 | F3: 2021-06-15 | G3: 400000000 | H3: 0.04
A4: R003 | B4: Nguyễn Lân | C4: Đà Nẵng | D4: nguyen.lan@company.com | E4: 0923333333 | F4: 2022-09-01 | G4: 200000000 | H4: 0.03
A5: R004 | B5: Lê Quân | C5: Hải Phòng | D5: le.quan@company.com | E5: 0934444444 | F5: 2023-01-10 | G5: 150000000 | H5: 0.03

Sheet orders
A1: order_id | B1: order_date | C1: customer_id | D1: rep_id | E1: status | F1: payment_method | G1: shipping_fee | H1: note
A2: ORD001 | B2: 2024-01-05 | C2: C001 | D2: R001 | E2: Hoàn thành | F2: Chuyển khoản | G2: 50000
A3: ORD002 | B3: 2024-01-08 | C3: C002 | D3: R002 | E3: Hoàn thành | F3: Tiền mặt | G3: 0 | H3: Khách lấy tại cửa hàng
A4: ORD003 | B4: 2024-01-12 | C4: C003 | D4: R003 | E4: Hoàn thành | F4: Chuyển khoản | G4: 80000
A5: ORD004 | B5: 2024-01-15 | C5: C001 | D5: R001 | E5: Hoàn thành | F5: Chuyển khoản | G5: 30000
A6: ORD005 | B6: 2024-01-20 | C6: C004 | D6: R004 | E6: Hoàn thành | F6: COD | G6: 50000
A7: ORD006 | B7: 2024-02-03 | C7: C005 | D7: R002 | E7: Hoàn thành | F7: Chuyển khoản | G7: 100000 | H7: Đơn hàng lớn
A8: ORD007 | B8: 2024-02-10 | C8: C006 | D8: R001 | E8: Hoàn thành | F8: Tiền mặt | G8: 0
A9: ORD008 | B9: 2024-02-14 | C9: C007 | D9: R003 | E9: Hoàn thành | F9: Chuyển khoản | G9: 60000
A10: ORD009 | B10: 2024-02-18 | C10: C008 | D10: R001 | E10: Hoàn thành | F10: Chuyển khoản | G10: 50000
A11: ORD010 | B11: 2024-02-22 | C11: C009 | D11: R002 | E11: Hoàn thành | F11: Thẻ tín dụng | G11: 0
A12: ORD011 | B12: 2024-03-01 | C12: C011 | D12: R003 | E12: Hoàn thành | F12: Chuyển khoản | G12: 50000
A13: ORD012 | B13: 2024-03-07 | C13: C001 | D13: R001 | E13: Hoàn thành | F13: Tiền mặt | G13: 0
A14: ORD013 | B14: 2024-03-15 | C14: C002 | D14: R002 | E14: Hoàn thành | F14: Thẻ tín dụng | G14: 50000
A15: ORD014 | B15: 2024-03-20 | C15: C006 | D15: R001 | E15: Hoàn thành | F15: Chuyển khoản | G15: 50000
A16: ORD015 | B16: 2024-03-28 | C16: C004 | D16: R004 | E16: Hoàn thành | F16: COD | G16: 80000
A17: ORD016 | B17: 2024-04-05 | C17: C009 | D17: R002 | E17: Hoàn thành | F17: Thẻ tín dụng | G17: 50000
A18: ORD017 | B18: 2024-04-10 | C18: C008 | D18: R001 | E18: Hoàn thành | F18: Chuyển khoản | G18: 30000
A19: ORD018 | B19: 2024-04-18 | C19: C004 | D19: R004 | E19: Hoàn thành | F19: COD | G19: 50000
... A31: ORD030 | B31: 2024-07-05 | C31: C012 | D31: R003 | E31: Hoàn thành | F31: Chuyển khoản | G31: 50000

Sheet order_details
A1: detail_id | B1: order_id | C1: product_id | D1: quantity | E1: unit_price | F1: discount_pct | G1: line_total
A2: D001 | B2: ORD001 | C2: P001 | D2: 2 | E2: 18500000 | F2: 0.05 | G2: =D2*E2*(1-F2)
A3: D002 | B3: ORD002 | C3: P004 | D3: 3 | E3: 22000000 | F3: 0 | G3: =D3*E3*(1-F3)
A4: D003 | B4: ORD003 | C4: P002 | D4: 1 | E4: 32000000 | F4: 0.1 | G4: =D4*E4*(1-F4)
A5: D004 | B5: ORD004 | C5: P008 | D5: 5 | E5: 1200000 | F5: 0 | G5: =D5*E5*(1-F5)
A6: D005 | B6: ORD005 | C6: P006 | D6: 2 | E6: 6500000 | F6: 0.05 | G6: =D6*E6*(1-F6)
A7: D006 | B7: ORD006 | C7: P001 | D7: 4 | E7: 18500000 | F7: 0.1 | G7: =D7*E7*(1-F7)
A8: D007 | B8: ORD007 | C8: P005 | D8: 2 | E8: 18000000 | F8: 0 | G8: =D8*E8*(1-F8)
A9: D008 | B9: ORD008 | C9: P010 | D9: 3 | E9: 2500000 | F9: 0.05 | G9: =D9*E9*(1-F9)
A10: D009 | B10: ORD009 | C10: P002 | D10: 2 | E10: 32000000 | F10: 0.15 | G10: =D10*E10*(1-F10)
A11: D010 | B11: ORD010 | C11: P007 | D11: 1 | E11: 4800000 | F11: 0 | G11: =D11*E11*(1-F11)
A12: D011 | B12: ORD011 | C12: P004 | D12: 1 | E12: 22000000 | F12: 0 | G12: =D12*E12*(1-F12)
A13: D012 | B13: ORD012 | C13: P009 | D13: 10 | E13: 850000 | F13: 0 | G13: =D13*E13*(1-F13)
... A33: D032 | B33: ORD030 | C33: P003 | D33: 1 | E33: 14000000 | F33: 0 | G33: =D33*E33*(1-F33)

Sheet summary
A1: 📊 TỔNG HỢP KINH DOANH — 2024
A2: Tổng đơn hàng | B2: Tổng doanh thu | C2: Trung bình/đơn | D2: Tổng SP bán ra
A4: =COUNTA(orders!A2:A1000)-1 | B4: =SUMIF(order_details!G2:G1000,">0",order_details!G2:G1000) | C4: =IF(A4>0,B4/A4,0) | D4: =SUM(order_details!D2:D1000)
A6: Rep | B6: Khu vực | C6: Số đơn | D6: Doanh thu | E6: % Tổng
A7: Trần Minh | B7: Hà Nội | C7: =COUNTIF(orders!D2:D1000,"R001") | D7: =SUMPRODUCT((orders!D2:D100="R001")*(IFERROR(VLOOKUP(orders!A2:A100,order_details!B2:G1000,6,0),0))) | E7: =IF($B$4>0,D7/$B$4,0)
A8: Phạm Hoa | B8: TP.HCM | C8: =COUNTIF(orders!D2:D1000,"R002") | D8: =SUMPRODUCT((orders!D2:D100="R002")*(IFERROR(VLOOKUP(orders!A2:A100,order_details!B2:G1000,6,0),0))) | E8: =IF($B$4>0,D8/$B$4,0)
A9: Nguyễn Lân | B9: Đà Nẵng | C9: =COUNTIF(orders!D2:D1000,"R003") | D9: =SUMPRODUCT((orders!D2:D100="R003")*(IFERROR(VLOOKUP(orders!A2:A100,order_details!B2:G1000,6,0),0))) | E9: =IF($B$4>0,D9/$B$4,0)
A10: Lê Quân | B10: Hải Phòng | C10: =COUNTIF(orders!D2:D1000,"R004") | D10: =SUMPRODUCT((orders!D2:D100="R004")*(IFERROR(VLOOKUP(orders!A2:A100,order_details!B2:G1000,6,0),0))) | E10: =IF($B$4>0,D10/$B$4,0)
A12: Danh mục | B12: Số lượng bán | C12: Doanh thu | D12: Tỷ trọng
A13: Laptop | B13: =SUMPRODUCT((ISNUMBER(MATCH(order_details!C2:C200,{"P001","P002","P003"},0)))*order_details!D2:D200) | C13: =SUMPRODUCT((ISNUMBER(MATCH(order_details!C2:C200,{"P001","P002","P003"},0)))*order_details!G2:G200) | D13: =IF($B$4>0,C13/SUM(C13:C16),0)
A14: Điện thoại | B14: =SUMPRODUCT((ISNUMBER(MATCH(order_details!C2:C200,{"P004","P005"},0)))*order_details!D2:D200) | C14: =SUMPRODUCT((ISNUMBER(MATCH(order_details!C2:C200,{"P004","P005"},0)))*order_details!G2:G200) | D14: =IF($B$4>0,C14/SUM(C13:C16),0)
A15: Màn hình | B15: =SUMPRODUCT((ISNUMBER(MATCH(order_details!C2:C200,{"P006","P007"},0)))*order_details!D2:D200) | C15: =SUMPRODUCT((ISNUMBER(MATCH(order_details!C2:C200,{"P006","P007"},0)))*order_details!G2:G200) | D15: =IF($B$4>0,C15/SUM(C13:C16),0)
A16: Phụ kiện | B16: =SUMPRODUCT((ISNUMBER(MATCH(order_details!C2:C200,{"P008","P009","P010","P011","P012"},0)))*order_details!D2:D200) | C16: =SUMPRODUCT((ISNUMBER(MATCH(order_details!C2:C200,{"P008","P009","P010","P011","P012"},0)))*order_details!G2:G200) | D16: =IF($B$4>0,C16/SUM(C13:C16),0)
